mercurytools/__init__.py
mercurytools/src/__init__.py
mercurytools/src/cli.py
mercurytools/src/core/__init__.py
mercurytools/src/core/exceptions.py
mercurytools/src/core/layout_linear.py
mercurytools/src/core/layout_tree.py
mercurytools/src/type/__init__.py
mercurytools/src/type/deque.py
mercurytools/src/type/linked_list.py
mercurytools/src/type/stack.py
mercurytools-1.0.0.dist-info/METADATA
mercurytools-1.0.0.dist-info/WHEEL
mercurytools-1.0.0.dist-info/top_level.txt
mercurytools-1.0.0.dist-info/RECORD
