Metadata-Version: 2.4
Name: mercurytools
Version: 1.0.0
Summary: python package to implement data structures
Author: Walter Michel Raja
Author-email: waltermichelraja@gmail.com
License: MIT
Classifier: License :: OSI Approved :: MIT License
Classifier: Programming Language :: Python :: 3
Classifier: Programming Language :: Python :: 3.9
Dynamic: author
Dynamic: author-email
Dynamic: classifier
Dynamic: description
Dynamic: description-content-type
Dynamic: license
Dynamic: summary
